fakers/__init__.py
fakers/logger_setup.py
fakers/.tests/person_test.py
fakers/.tests/retail_test.py
fakers/bl/__init__.py
fakers/bl/address.py
fakers/bl/person.py
fakers/bl/retail/__init__.py
fakers/bl/retail/order.py
fakers/bl/retail/product.py
fakers/bl/retail/sales.py
fakers/bl/retail/user.py
fakers/providers/__init__.py
fakers/providers/person.py
fakers/providers/retail.py
fakers/utils/__init__.py
fakers-0.4.0.dist-info/LICENSE
fakers-0.4.0.dist-info/WHEEL
fakers-0.4.0.dist-info/METADATA
fakers-0.4.0.dist-info/RECORD
