Metadata-Version: 2.1
Name: fakers
Version: 0.4.0
Summary: A package that provides ready-made objects of fake-data.
Author-email: ASHISH GARG <ashishgargmp@gmail.com>
Requires-Python: >=3.6
Requires-Dist: Faker
Requires-Dist: pandas
Requires-Dist: pyspark
Requires-Dist: pytest ; extra == "test"
Requires-Dist: pytest-cov ; extra == "test"
Provides-Extra: test
